byted_overpass_ad_genai_product_material_generation/__init__.py
byted_overpass_ad_genai_product_material_generation-0.0.1.dist-info/METADATA
byted_overpass_ad_genai_product_material_generation-0.0.1.dist-info/WHEEL
byted_overpass_ad_genai_product_material_generation-0.0.1.dist-info/top_level.txt
byted_overpass_ad_genai_product_material_generation-0.0.1.dist-info/RECORD
